khoj/__init__.py
khoj/khoj.py
khoj-cli/__init__.py
khoj-cli/khoj.py
khoj_cli-0.1.dist-info/METADATA
khoj_cli-0.1.dist-info/WHEEL
khoj_cli-0.1.dist-info/entry_points.txt
khoj_cli-0.1.dist-info/top_level.txt
khoj_cli-0.1.dist-info/RECORD
