Metadata-Version: 2.1
Name: khoj-cli
Version: 0.1
Summary: CLI tool for searching using Khoj
Home-page: https://github.com/ajinkgupta/khoj-cli
Author: Ajink Gupta
Author-email: guptaajink21@gmail.com
License: MIT
Classifier: Development Status :: 3 - Alpha
Classifier: Intended Audience :: Developers
Classifier: Programming Language :: Python :: 3
Requires-Dist: requests
Requires-Dist: colorama
